graphinglib/__init__.py
graphinglib/_version.py
graphinglib/data_plotting_1d.py
graphinglib/data_plotting_2d.py
graphinglib/default_styles/dark.yml
graphinglib/default_styles/dim.yml
graphinglib/default_styles/horrible.yml
graphinglib/default_styles/plain.yml
graphinglib/figure.py
graphinglib/file_manager.py
graphinglib/fits.py
graphinglib/graph_elements.py
graphinglib/legend_artists.py
graphinglib/multifigure.py
graphinglib/shapes.py
graphinglib-1.5.0.dist-info/LICENSE
graphinglib-1.5.0.dist-info/METADATA
graphinglib-1.5.0.dist-info/WHEEL
graphinglib-1.5.0.dist-info/RECORD
