Metadata-Version: 2.1
Name: graphinglib
Version: 1.5.0
Summary: An object oriented wrapper combining the functionalities of Matplotlib and Scipy
License: MIT
Author: Gustave Coulombe
Author-email: magikgus@gmail.com
Requires-Python: >=3.10,<3.13
Classifier: License :: OSI Approved :: MIT License
Classifier: Programming Language :: Python :: 3
Classifier: Programming Language :: Python :: 3.10
Classifier: Programming Language :: Python :: 3.11
Classifier: Programming Language :: Python :: 3.12
Requires-Dist: PyYAML (>=6.0,<7.0)
Requires-Dist: matplotlib (>=3.7.1,<4.0.0)
Requires-Dist: numpy (>=1.24.2,<2.0.0)
Requires-Dist: platformdirs (>=3.11.0,<4.0.0)
Requires-Dist: scipy (>=1.10.1,<2.0.0)
Requires-Dist: setuptools-scm (>=8.0.4,<9.0.0)
Requires-Dist: shapely (>=2.0.3,<3.0.0)
